tensorcraft_py/__init__.py
tensorcraft_py/tf_dataclasses.py
tensorcraft_py-0.0.26.dist-info/METADATA
tensorcraft_py-0.0.26.dist-info/WHEEL
tensorcraft_py-0.0.26.dist-info/licenses/LICENSE
tensorcraft_py-0.0.26.dist-info/RECORD
