Metadata-Version: 2.1
Name: tensorcraft_py
Version: 0.0.26
Summary: Python lib for accessing the Tensorcraft.com API.
Project-URL: Homepage, https://github.com/cloudwow/tensorcraft_py
Project-URL: Bug Tracker, https://github.com/cloudwow/tensorcraft_py/issues
Author-email: David Knight <david@knight.fm>
License: MIT License
License-File: LICENSE
Classifier: License :: OSI Approved :: MIT License
Classifier: Operating System :: OS Independent
Classifier: Programming Language :: Python :: 3
Requires-Python: >=3.7
Requires-Dist: dataclasses-json>=0.5.7
